Metadata-Version: 2.0
Name: twitter.common.fs
Version: 0.3.11
Summary: Filesystem utilities for twitter.
Home-page: https://github.com/twitter/commons/tree/master/src/python/twitter/common/fs
Author: UNKNOWN
Author-email: UNKNOWN
License: Apache License, Version 2.0
Platform: UNKNOWN
Classifier: Intended Audience :: Developers
Classifier: License :: OSI Approved :: Apache Software License
Classifier: Operating System :: OS Independent
Classifier: Programming Language :: Python
Requires-Dist: twitter.common.contextutil (==0.3.11)
Requires-Dist: twitter.common.quantity (==0.3.11)
Requires-Dist: twitter.common.string (==0.3.11)
Requires-Dist: twitter.common.util (==0.3.11)
